panda_py/libfranka.cpython-39-x86_64-linux-gnu.so
panda_py/_core.cpython-39-x86_64-linux-gnu.so
panda_py/py.typed
panda_py/motion.py
panda_py/cli.py
panda_py/__init__.pyi
panda_py/libfranka.pyi
panda_py/controllers.py
panda_py/_core.pyi
panda_py/constants.py
panda_py/__init__.py
panda_python.libs/libfranka-5b0ac581.so.0.9.2
panda_python.libs/libPocoFoundation-46248de0.so.62
panda_python.libs/libPocoNet-e9b878d5.so.62
panda_python-0.8.1.dist-info/entry_points.txt
panda_python-0.8.1.dist-info/WHEEL
panda_python-0.8.1.dist-info/RECORD
panda_python-0.8.1.dist-info/METADATA
panda_python-0.8.1.dist-info/licenses/LICENSE
