Metadata-Version: 2.1
Name: panda-python
Version: 0.8.1
Summary: Python bindings for the Panda robot
Keywords: python,real-time,control,robot,franka,emika
Author-Email: Jean Elsner <jean.elsner@tum.de>
License:                                  Apache License
Classifier: Intended Audience :: Science/Research
Classifier: Intended Audience :: Developers
Classifier: License :: OSI Approved :: Apache Software License
Classifier: Topic :: Scientific/Engineering
Classifier: Programming Language :: Python :: 3.7
Classifier: Programming Language :: Python :: 3.8
Classifier: Programming Language :: Python :: 3.9
Classifier: Programming Language :: Python :: 3.10
Classifier: Programming Language :: Python :: 3.11
Classifier: Programming Language :: Python :: 3.12
Requires-Python: >=3.7
Requires-Dist: websockets>=11.0
Requires-Dist: requests
Requires-Dist: numpy
Requires-Dist: roboticstoolbox-python; extra == "examples"
Requires-Dist: matplotlib; extra == "examples"
Requires-Dist: spatialmath-python; extra == "examples"
Requires-Dist: ansitable; extra == "examples"
Requires-Dist: qpsolvers; extra == "examples"
Requires-Dist: furo; extra == "docs"
Requires-Dist: sphinx-reredirects; extra == "docs"
Requires-Dist: sphinx; extra == "docs"
Requires-Dist: pybind11-stubgen; extra == "dev"
Provides-Extra: examples
Provides-Extra: docs
Provides-Extra: dev
